{
  "Bottombar": {
    "menuAlt": "\uDB40\uDC3Cmenu latéral ouvert\uDB40\uDC40\uDB40\uDC32\uDB40\uDC39\uDB40\uDC39\uDB40\uDC35\uDB40\uDC5F\uDB40\uDC31\uDB40\uDC37\uDB40\uDC33\uDB40\uDC3E"
  },
  "Browse": {
    "droidTitle": "\uDB40\uDC3CTous les droïdes\uDB40\uDC40\uDB40\uDC32\uDB40\uDC39\uDB40\uDC35\uDB40\uDC32\uDB40\uDC5F\uDB40\uDC31\uDB40\uDC37\uDB40\uDC33\uDB40\uDC3E",
    "vehicleTitle": "\uDB40\uDC3CTous les véhicules\uDB40\uDC40\uDB40\uDC32\uDB40\uDC39\uDB40\uDC35\uDB40\uDC33\uDB40\uDC5F\uDB40\uDC31\uDB40\uDC37\uDB40\uDC33\uDB40\uDC3E"
  },
  "Cart": {
    "cartTitle": "\uDB40\uDC3CPanier\uDB40\uDC40\uDB40\uDC32\uDB40\uDC39\uDB40\uDC38\uDB40\uDC33\uDB40\uDC5F\uDB40\uDC31\uDB40\uDC37\uDB40\uDC33\uDB40\uDC3E",
    "checkoutLabel": "\uDB40\uDC3CCONTRÔLE\uDB40\uDC40\uDB40\uDC32\uDB40\uDC39\uDB40\uDC38\uDB40\uDC37\uDB40\uDC5F\uDB40\uDC31\uDB40\uDC37\uDB40\uDC33\uDB40\uDC3E",
    "closeAlt": "\uDB40\uDC3CFermer le chariot\uDB40\uDC40\uDB40\uDC32\uDB40\uDC39\uDB40\uDC38\uDB40\uDC38\uDB40\uDC5F\uDB40\uDC31\uDB40\uDC37\uDB40\uDC33\uDB40\uDC3E",
    "deleteAlt": "\uDB40\uDC3CSupprimer l'élément du chariot\uDB40\uDC40\uDB40\uDC32\uDB40\uDC39\uDB40\uDC38\uDB40\uDC35\uDB40\uDC5F\uDB40\uDC31\uDB40\uDC37\uDB40\uDC33\uDB40\uDC3E",
    "noItemMsg": "\uDB40\uDC3CAucun objet dans le chariot.\uDB40\uDC40\uDB40\uDC32\uDB40\uDC39\uDB40\uDC38\uDB40\uDC34\uDB40\uDC5F\uDB40\uDC31\uDB40\uDC37\uDB40\uDC33\uDB40\uDC3E",
    "totalTitle": "\uDB40\uDC3CTotal : \uDB40\uDC40\uDB40\uDC32\uDB40\uDC39\uDB40\uDC38\uDB40\uDC36\uDB40\uDC5F\uDB40\uDC31\uDB40\uDC37\uDB40\uDC33\uDB40\uDC3E"
  },
  "Checkout": {
    "accountHolder": "\uDB40\uDC3C1234567-9876-00\uDB40\uDC40\uDB40\uDC32\uDB40\uDC39\uDB40\uDC36\uDB40\uDC39\uDB40\uDC5F\uDB40\uDC31\uDB40\uDC37\uDB40\uDC33\uDB40\uDC3E",
    "accountLabel": "\uDB40\uDC3CNuméro de crédit Imperial\uDB40\uDC40\uDB40\uDC32\uDB40\uDC39\uDB40\uDC36\uDB40\uDC38\uDB40\uDC5F\uDB40\uDC31\uDB40\uDC37\uDB40\uDC33\uDB40\uDC3E",
    "cartTitle": "\uDB40\uDC3CPanier\uDB40\uDC40\uDB40\uDC32\uDB40\uDC39\uDB40\uDC37\uDB40\uDC33\uDB40\uDC5F\uDB40\uDC31\uDB40\uDC37\uDB40\uDC33\uDB40\uDC3E",
    "checkoutTitle": "\uDB40\uDC3CConclusion de la transaction\uDB40\uDC40\uDB40\uDC32\uDB40\uDC39\uDB40\uDC35\uDB40\uDC34\uDB40\uDC5F\uDB40\uDC31\uDB40\uDC37\uDB40\uDC33\uDB40\uDC3E",
    "coordinatesHolder": "\uDB40\uDC3C0,0,0,0\uDB40\uDC40\uDB40\uDC32\uDB40\uDC39\uDB40\uDC35\uDB40\uDC39\uDB40\uDC5F\uDB40\uDC31\uDB40\uDC37\uDB40\uDC33\uDB40\uDC3E",
    "coordinatesLabel": "\uDB40\uDC3CCoordonnées\uDB40\uDC40\uDB40\uDC32\uDB40\uDC39\uDB40\uDC35\uDB40\uDC38\uDB40\uDC5F\uDB40\uDC31\uDB40\uDC37\uDB40\uDC33\uDB40\uDC3E",
    "deleteAlt": "\uDB40\uDC3Csupprimer l'élément du chariot\uDB40\uDC40\uDB40\uDC32\uDB40\uDC39\uDB40\uDC37\uDB40\uDC34\uDB40\uDC5F\uDB40\uDC31\uDB40\uDC37\uDB40\uDC33\uDB40\uDC3E",
    "expDateLabel": "\uDB40\uDC3CDate d'expiration\uDB40\uDC40\uDB40\uDC32\uDB40\uDC39\uDB40\uDC37\uDB40\uDC32\uDB40\uDC5F\uDB40\uDC31\uDB40\uDC37\uDB40\uDC33\uDB40\uDC3E",
    "firstNameLabel": "\uDB40\uDC3CPrénom\uDB40\uDC40\uDB40\uDC32\uDB40\uDC39\uDB40\uDC35\uDB40\uDC36\uDB40\uDC5F\uDB40\uDC31\uDB40\uDC37\uDB40\uDC33\uDB40\uDC3E",
    "lastNameLabel": "\uDB40\uDC3CNom de famille\uDB40\uDC40\uDB40\uDC32\uDB40\uDC39\uDB40\uDC35\uDB40\uDC37\uDB40\uDC5F\uDB40\uDC31\uDB40\uDC37\uDB40\uDC33\uDB40\uDC3E",
    "methodLabel": "\uDB40\uDC3CMode d'expédition\uDB40\uDC40\uDB40\uDC32\uDB40\uDC39\uDB40\uDC36\uDB40\uDC31\uDB40\uDC5F\uDB40\uDC31\uDB40\uDC37\uDB40\uDC33\uDB40\uDC3E",
    "noItemMessage": "\uDB40\uDC3CAjouter des éléments au chariot à retirer.\uDB40\uDC40\uDB40\uDC32\uDB40\uDC39\uDB40\uDC38\uDB40\uDC30\uDB40\uDC5F\uDB40\uDC31\uDB40\uDC37\uDB40\uDC33\uDB40\uDC3E",
    "orderLabel": "\uDB40\uDC3CORDRE DE PLACE\uDB40\uDC40\uDB40\uDC32\uDB40\uDC39\uDB40\uDC37\uDB40\uDC36\uDB40\uDC5F\uDB40\uDC31\uDB40\uDC37\uDB40\uDC33\uDB40\uDC3E",
    "payNameHolder": "\uDB40\uDC3CPremier dernier\uDB40\uDC40\uDB40\uDC32\uDB40\uDC39\uDB40\uDC36\uDB40\uDC37\uDB40\uDC5F\uDB40\uDC31\uDB40\uDC37\uDB40\uDC33\uDB40\uDC3E",
    "payNameLabel": "\uDB40\uDC3CNom de la carte\uDB40\uDC40\uDB40\uDC32\uDB40\uDC39\uDB40\uDC36\uDB40\uDC36\uDB40\uDC5F\uDB40\uDC31\uDB40\uDC37\uDB40\uDC33\uDB40\uDC3E",
    "paySectionLabel": "\uDB40\uDC3CPaiement\uDB40\uDC40\uDB40\uDC32\uDB40\uDC39\uDB40\uDC36\uDB40\uDC35\uDB40\uDC5F\uDB40\uDC31\uDB40\uDC37\uDB40\uDC33\uDB40\uDC3E",
    "sectorLabel": "\uDB40\uDC3CSecteur/Quadrant\uDB40\uDC40\uDB40\uDC32\uDB40\uDC39\uDB40\uDC36\uDB40\uDC30\uDB40\uDC5F\uDB40\uDC31\uDB40\uDC37\uDB40\uDC33\uDB40\uDC3E",
    "securityHolder": "\uDB40\uDC3C123456\uDB40\uDC40\uDB40\uDC32\uDB40\uDC39\uDB40\uDC37\uDB40\uDC31\uDB40\uDC5F\uDB40\uDC31\uDB40\uDC37\uDB40\uDC33\uDB40\uDC3E",
    "securityLabel": "\uDB40\uDC3CCode de sécurité\uDB40\uDC40\uDB40\uDC32\uDB40\uDC39\uDB40\uDC37\uDB40\uDC30\uDB40\uDC5F\uDB40\uDC31\uDB40\uDC37\uDB40\uDC33\uDB40\uDC3E",
    "shipLightspeed": "\uDB40\uDC3CVitesse lumineuse\uDB40\uDC40\uDB40\uDC32\uDB40\uDC39\uDB40\uDC36\uDB40\uDC32\uDB40\uDC5F\uDB40\uDC31\uDB40\uDC37\uDB40\uDC33\uDB40\uDC3E",
    "shipOvernight": "\uDB40\uDC3CNuit\uDB40\uDC40\uDB40\uDC32\uDB40\uDC39\uDB40\uDC36\uDB40\uDC33\uDB40\uDC5F\uDB40\uDC31\uDB40\uDC37\uDB40\uDC33\uDB40\uDC3E",
    "shipSectionLabel": "\uDB40\uDC3CInformations sur l'expédition\uDB40\uDC40\uDB40\uDC32\uDB40\uDC39\uDB40\uDC35\uDB40\uDC35\uDB40\uDC5F\uDB40\uDC31\uDB40\uDC37\uDB40\uDC33\uDB40\uDC3E",
    "shipStandard": "\uDB40\uDC3CStandard\uDB40\uDC40\uDB40\uDC32\uDB40\uDC39\uDB40\uDC36\uDB40\uDC34\uDB40\uDC5F\uDB40\uDC31\uDB40\uDC37\uDB40\uDC33\uDB40\uDC3E",
    "successMessage": "\uDB40\uDC3CCommande passée avec succès !\uDB40\uDC40\uDB40\uDC32\uDB40\uDC39\uDB40\uDC37\uDB40\uDC39\uDB40\uDC5F\uDB40\uDC31\uDB40\uDC37\uDB40\uDC33\uDB40\uDC3E",
    "termsLink": "\uDB40\uDC3C(Affichage)\uDB40\uDC40\uDB40\uDC32\uDB40\uDC39\uDB40\uDC37\uDB40\uDC38\uDB40\uDC5F\uDB40\uDC31\uDB40\uDC37\uDB40\uDC33\uDB40\uDC3E",
    "termsStatement": "\uDB40\uDC3CJ'ai lu et j'accepte les conditions générales\uDB40\uDC40\uDB40\uDC32\uDB40\uDC39\uDB40\uDC37\uDB40\uDC37\uDB40\uDC5F\uDB40\uDC31\uDB40\uDC37\uDB40\uDC33\uDB40\uDC3E",
    "totalLabel": "\uDB40\uDC3CTotal : \uDB40\uDC40\uDB40\uDC32\uDB40\uDC39\uDB40\uDC37\uDB40\uDC35\uDB40\uDC5F\uDB40\uDC31\uDB40\uDC37\uDB40\uDC33\uDB40\uDC3E"
  },
  "Error404": {
    "errorMessage": "\uDB40\uDC3C404 Erreur: Page introuvable.\uDB40\uDC40\uDB40\uDC32\uDB40\uDC39\uDB40\uDC39\uDB40\uDC34\uDB40\uDC5F\uDB40\uDC31\uDB40\uDC37\uDB40\uDC33\uDB40\uDC3E"
  },
  "Hamburger": {
    "contactLabel": "\uDB40\uDC3CContactez-nous\uDB40\uDC40\uDB40\uDC33\uDB40\uDC30\uDB40\uDC31\uDB40\uDC31\uDB40\uDC5F\uDB40\uDC31\uDB40\uDC37\uDB40\uDC33\uDB40\uDC3E",
    "dashLabel": "\uDB40\uDC3CAfficher le tableau de bord Lingoport\uDB40\uDC40\uDB40\uDC33\uDB40\uDC30\uDB40\uDC31\uDB40\uDC30\uDB40\uDC5F\uDB40\uDC31\uDB40\uDC37\uDB40\uDC33\uDB40\uDC3E",
    "githubLabel": "\uDB40\uDC3CAfficher la source\uDB40\uDC40\uDB40\uDC33\uDB40\uDC30\uDB40\uDC30\uDB40\uDC39\uDB40\uDC5F\uDB40\uDC31\uDB40\uDC37\uDB40\uDC33\uDB40\uDC3E",
    "githubLogoAlt": "\uDB40\uDC3CLogo GitHub\uDB40\uDC40\uDB40\uDC32\uDB40\uDC39\uDB40\uDC39\uDB40\uDC36\uDB40\uDC5F\uDB40\uDC31\uDB40\uDC37\uDB40\uDC33\uDB40\uDC3E",
    "learnLabel": "\uDB40\uDC3CEn savoir plus\uDB40\uDC40\uDB40\uDC33\uDB40\uDC30\uDB40\uDC31\uDB40\uDC32\uDB40\uDC5F\uDB40\uDC31\uDB40\uDC37\uDB40\uDC33\uDB40\uDC3E",
    "lingoLogoAlt": "\uDB40\uDC3CLogo de Lingoport\uDB40\uDC40\uDB40\uDC32\uDB40\uDC39\uDB40\uDC39\uDB40\uDC37\uDB40\uDC5F\uDB40\uDC31\uDB40\uDC37\uDB40\uDC33\uDB40\uDC3E",
    "localeEN": "\uDB40\uDC3CAnglais - États-Unis\uDB40\uDC40\uDB40\uDC33\uDB40\uDC30\uDB40\uDC30\uDB40\uDC33\uDB40\uDC5F\uDB40\uDC31\uDB40\uDC37\uDB40\uDC33\uDB40\uDC3E",
    "localeEO": "\uDB40\uDC3CEspéranto\uDB40\uDC40\uDB40\uDC33\uDB40\uDC30\uDB40\uDC30\uDB40\uDC38\uDB40\uDC5F\uDB40\uDC31\uDB40\uDC37\uDB40\uDC33\uDB40\uDC3E",
    "localeFR": "\uDB40\uDC3CFrançais - France\uDB40\uDC40\uDB40\uDC33\uDB40\uDC30\uDB40\uDC30\uDB40\uDC34\uDB40\uDC5F\uDB40\uDC31\uDB40\uDC37\uDB40\uDC33\uDB40\uDC3E",
    "localeLabel": "\uDB40\uDC3CLocale : \uDB40\uDC40\uDB40\uDC33\uDB40\uDC30\uDB40\uDC30\uDB40\uDC32\uDB40\uDC5F\uDB40\uDC31\uDB40\uDC37\uDB40\uDC33\uDB40\uDC3E",
    "localeSI": "\uDB40\uDC3CSith\uDB40\uDC40\uDB40\uDC33\uDB40\uDC30\uDB40\uDC30\uDB40\uDC37\uDB40\uDC5F\uDB40\uDC31\uDB40\uDC37\uDB40\uDC33\uDB40\uDC3E",
    "localeYO": "\uDB40\uDC3CYoda\uDB40\uDC40\uDB40\uDC33\uDB40\uDC30\uDB40\uDC30\uDB40\uDC36\uDB40\uDC5F\uDB40\uDC31\uDB40\uDC37\uDB40\uDC33\uDB40\uDC3E",
    "localeZH": "\uDB40\uDC3CChinois - Chine\uDB40\uDC40\uDB40\uDC33\uDB40\uDC30\uDB40\uDC30\uDB40\uDC35\uDB40\uDC5F\uDB40\uDC31\uDB40\uDC37\uDB40\uDC33\uDB40\uDC3E",
    "versionBad": "\uDB40\uDC3CNon-i18n compatible\uDB40\uDC40\uDB40\uDC32\uDB40\uDC39\uDB40\uDC39\uDB40\uDC39\uDB40\uDC5F\uDB40\uDC31\uDB40\uDC37\uDB40\uDC33\uDB40\uDC3E",
    "versionGood": "\uDB40\uDC3CConformité I18n\uDB40\uDC40\uDB40\uDC33\uDB40\uDC30\uDB40\uDC30\uDB40\uDC30\uDB40\uDC5F\uDB40\uDC31\uDB40\uDC37\uDB40\uDC33\uDB40\uDC3E",
    "versionIQA": "\uDB40\uDC3CTraduction InContext\uDB40\uDC40\uDB40\uDC33\uDB40\uDC30\uDB40\uDC30\uDB40\uDC31\uDB40\uDC5F\uDB40\uDC31\uDB40\uDC37\uDB40\uDC33\uDB40\uDC3E",
    "versionLabel": "\uDB40\uDC3CVersion: \uDB40\uDC40\uDB40\uDC32\uDB40\uDC39\uDB40\uDC39\uDB40\uDC38\uDB40\uDC5F\uDB40\uDC31\uDB40\uDC37\uDB40\uDC33\uDB40\uDC3E"
  },
  "Home": {
    "symbolAlt": "\uDB40\uDC3CSymbole monétaire Imperial Credit\uDB40\uDC40\uDB40\uDC32\uDB40\uDC39\uDB40\uDC35\uDB40\uDC31\uDB40\uDC5F\uDB40\uDC31\uDB40\uDC37\uDB40\uDC33\uDB40\uDC3E",
    "welcomeMessage": "\uDB40\uDC3CBienvenue chez Rebel Outfitters !\uDB40\uDC40\uDB40\uDC32\uDB40\uDC39\uDB40\uDC34\uDB40\uDC39\uDB40\uDC5F\uDB40\uDC31\uDB40\uDC37\uDB40\uDC33\uDB40\uDC3E",
    "welcomeSubtitle": "\uDB40\uDC3CNous fournissons tout ce dont vous avez besoin pour affronter l'Empire (et les écraser).\uDB40\uDC40\uDB40\uDC32\uDB40\uDC39\uDB40\uDC35\uDB40\uDC30\uDB40\uDC5F\uDB40\uDC31\uDB40\uDC37\uDB40\uDC33\uDB40\uDC3E"
  },
  "Navbar": {
    "arrowAlt": "\uDB40\uDC3CFlèche vers le bas\uDB40\uDC40\uDB40\uDC32\uDB40\uDC39\uDB40\uDC34\uDB40\uDC34\uDB40\uDC5F\uDB40\uDC31\uDB40\uDC37\uDB40\uDC33\uDB40\uDC3E",
    "cartAlt": "\uDB40\uDC3Cafficher le chariot\uDB40\uDC40\uDB40\uDC32\uDB40\uDC39\uDB40\uDC34\uDB40\uDC35\uDB40\uDC5F\uDB40\uDC31\uDB40\uDC37\uDB40\uDC33\uDB40\uDC3E",
    "greetingText": "\uDB40\uDC3CSalut Han\uDB40\uDC40\uDB40\uDC32\uDB40\uDC39\uDB40\uDC34\uDB40\uDC32\uDB40\uDC5F\uDB40\uDC31\uDB40\uDC37\uDB40\uDC33\uDB40\uDC3E",
    "historyLink": "\uDB40\uDC3CHISTOIRE DE L'ORDRE\uDB40\uDC40\uDB40\uDC32\uDB40\uDC39\uDB40\uDC34\uDB40\uDC33\uDB40\uDC5F\uDB40\uDC31\uDB40\uDC37\uDB40\uDC33\uDB40\uDC3E",
    "logoAlt": "\uDB40\uDC3CLogo Rebel Outfitters\uDB40\uDC40\uDB40\uDC32\uDB40\uDC39\uDB40\uDC34\uDB40\uDC30\uDB40\uDC5F\uDB40\uDC31\uDB40\uDC37\uDB40\uDC33\uDB40\uDC3E",
    "navLinkDroids": "\uDB40\uDC3CDROIDS\uDB40\uDC40\uDB40\uDC32\uDB40\uDC39\uDB40\uDC34\uDB40\uDC37\uDB40\uDC5F\uDB40\uDC31\uDB40\uDC37\uDB40\uDC33\uDB40\uDC3E",
    "navLinkHome": "\uDB40\uDC3CMAISON\uDB40\uDC40\uDB40\uDC32\uDB40\uDC39\uDB40\uDC34\uDB40\uDC36\uDB40\uDC5F\uDB40\uDC31\uDB40\uDC37\uDB40\uDC33\uDB40\uDC3E",
    "navLinkVehicles": "\uDB40\uDC3CVÉHICULES\uDB40\uDC40\uDB40\uDC32\uDB40\uDC39\uDB40\uDC34\uDB40\uDC38\uDB40\uDC5F\uDB40\uDC31\uDB40\uDC37\uDB40\uDC33\uDB40\uDC3E",
    "searchButtonLabel": "\uDB40\uDC3Cproduits de recherche\uDB40\uDC40\uDB40\uDC32\uDB40\uDC39\uDB40\uDC33\uDB40\uDC39\uDB40\uDC5F\uDB40\uDC31\uDB40\uDC37\uDB40\uDC33\uDB40\uDC3E",
    "searchIconAlt": "\uDB40\uDC3Cicône de recherche\uDB40\uDC40\uDB40\uDC32\uDB40\uDC39\uDB40\uDC34\uDB40\uDC31\uDB40\uDC5F\uDB40\uDC31\uDB40\uDC37\uDB40\uDC33\uDB40\uDC3E",
    "searchPlaceholder": "\uDB40\uDC3CQue cherches-tu ?\uDB40\uDC40\uDB40\uDC32\uDB40\uDC39\uDB40\uDC33\uDB40\uDC38\uDB40\uDC5F\uDB40\uDC31\uDB40\uDC37\uDB40\uDC33\uDB40\uDC3E"
  },
  "OrderHistory": {
    "dateHeading": "\uDB40\uDC3CDate\uDB40\uDC40\uDB40\uDC32\uDB40\uDC39\uDB40\uDC39\uDB40\uDC30\uDB40\uDC5F\uDB40\uDC31\uDB40\uDC37\uDB40\uDC33\uDB40\uDC3E",
    "historyTitle": "\uDB40\uDC3CHistorique des commandes\uDB40\uDC40\uDB40\uDC32\uDB40\uDC39\uDB40\uDC38\uDB40\uDC39\uDB40\uDC5F\uDB40\uDC31\uDB40\uDC37\uDB40\uDC33\uDB40\uDC3E",
    "numberHeading": "\uDB40\uDC3CNuméro de commande\uDB40\uDC40\uDB40\uDC32\uDB40\uDC39\uDB40\uDC39\uDB40\uDC31\uDB40\uDC5F\uDB40\uDC31\uDB40\uDC37\uDB40\uDC33\uDB40\uDC3E",
    "statusHeading": "\uDB40\uDC3CStatut\uDB40\uDC40\uDB40\uDC32\uDB40\uDC39\uDB40\uDC39\uDB40\uDC33\uDB40\uDC5F\uDB40\uDC31\uDB40\uDC37\uDB40\uDC33\uDB40\uDC3E",
    "totalHeading": "\uDB40\uDC3CTotal\uDB40\uDC40\uDB40\uDC32\uDB40\uDC39\uDB40\uDC39\uDB40\uDC32\uDB40\uDC5F\uDB40\uDC31\uDB40\uDC37\uDB40\uDC33\uDB40\uDC3E"
  },
  "Order": {
    "statusDelivered": "\uDB40\uDC3CLivré\uDB40\uDC40\uDB40\uDC33\uDB40\uDC30\uDB40\uDC31\uDB40\uDC35\uDB40\uDC5F\uDB40\uDC31\uDB40\uDC37\uDB40\uDC33\uDB40\uDC3E",
    "statusProcessing": "\uDB40\uDC3CTraitement\uDB40\uDC40\uDB40\uDC33\uDB40\uDC30\uDB40\uDC31\uDB40\uDC33\uDB40\uDC5F\uDB40\uDC31\uDB40\uDC37\uDB40\uDC33\uDB40\uDC3E",
    "statusShipped": "\uDB40\uDC3CExpédié\uDB40\uDC40\uDB40\uDC33\uDB40\uDC30\uDB40\uDC31\uDB40\uDC34\uDB40\uDC5F\uDB40\uDC31\uDB40\uDC37\uDB40\uDC33\uDB40\uDC3E"
  },
  "ProductShow": {
    "addToCartLabel": "\uDB40\uDC3CAJOUTER À LA CARTE\uDB40\uDC40\uDB40\uDC32\uDB40\uDC39\uDB40\uDC38\uDB40\uDC32\uDB40\uDC5F\uDB40\uDC31\uDB40\uDC37\uDB40\uDC33\uDB40\uDC3E",
    "qtyLabel": "\uDB40\uDC3CQté : \uDB40\uDC40\uDB40\uDC32\uDB40\uDC39\uDB40\uDC38\uDB40\uDC31\uDB40\uDC5F\uDB40\uDC31\uDB40\uDC37\uDB40\uDC33\uDB40\uDC3E"
  },
  "Special": "\uDB40\uDC3CSpécial\uDB40\uDC40\uDB40\uDC33\uDB40\uDC30\uDB40\uDC31\uDB40\uDC36\uDB40\uDC5F\uDB40\uDC31\uDB40\uDC37\uDB40\uDC33\uDB40\uDC3E",
  "desc": {
    "1": "\uDB40\uDC3CChaque droid est équipé d'un VerboBrain SyntheTech AA-1 qui lui permet de stocker d'énormes quantités d'informations, l'espace mémoire supplémentaire est souvent utilisé pour garder les modules de communication dans la mémoire active afin d'éviter de longs retards lors de la recherche d'informations linguistiques sur la traduction intermédiaire. Un module de communication TranLang III leur permet de parler couramment plus de six millions de formes de communication. Ils ont aussi les compétences nécessaires pour analyser rapidement les nouvelles langues non enregistrées et les traduire en langues plus connues.\uDB40\uDC40\uDB40\uDC32\uDB40\uDC39\uDB40\uDC32\uDB40\uDC35\uDB40\uDC5F\uDB40\uDC31\uDB40\uDC37\uDB40\uDC33\uDB40\uDC3E",
    "10": "\uDB40\uDC3CLe droid astromech de la série R3 est doté d'une grande partie du même matériel que son prédécesseur, l'unité R2, qui ne possède que le capteur vidéo extensible du droid précédent. Le châssis du R3 est en grande partie cylindrique et apparaît comme un tube droit avec un cône court et tronqué à sa base. Garder la droïde en position verticale sont deux jambes étroites, chacune se terminant dans un pied tressé en forme de prismes trapézoïdaux, une troisième jambe est logée dans le corps droïde et pourrait être prolongée si nécessaire pour assurer une plus grande stabilité. Le recouvrement de la conception de l'unité est un dôme robuste, rotatif, plastex ou transparent. L'astromech est scellé pour permettre la fonctionnalité dans le vide de l'espace.\uDB40\uDC40\uDB40\uDC32\uDB40\uDC39\uDB40\uDC33\uDB40\uDC34\uDB40\uDC5F\uDB40\uDC31\uDB40\uDC37\uDB40\uDC33\uDB40\uDC3E",
    "11": "\uDB40\uDC3CLe T-70 X-wing starfighter est un starfighter cruciforme mesurant 12,48 mètres de longueur et doté d'une capacité maximale d'un seul pilote et d'une droïde astromech à chargement inférieur, qui s'insère dans un support et peut être configuré de façon variable pour différents modèles. Si nécessaire, le droid peut piloter le starfighter sans l'aide d'un pilote, et peut même le faire à distance. L'ordinateur de ciblage du navire, les commandes de vol et d'autres instruments de pilotage essentiels sont situés à l'intérieur d'un module de cockpit blindé, sous lequel un ordinateur de vol amovible refroidi par liquide aide encore davantage le pilote dans les opérations maritimes. Il existe des panneaux d'accès pour l'accès et l'entreposage par ordinateur à l'intérieur du \"nez\" du navire, ainsi qu'un générateur auxiliaire et une aire de stockage habituellement utilisés pour l'arrimage des engins de survie. Une petite fenêtre de capteur indique l'emplacement de la baie de capteurs primaires des navires à la pointe même du nez, située derrière une balise de détresse. Derrière le pilote, un système intégré de soutien de la vie permet à l'occupant de respirer dans une atmosphère oxygénée.\uDB40\uDC40\uDB40\uDC32\uDB40\uDC39\uDB40\uDC33\uDB40\uDC35\uDB40\uDC5F\uDB40\uDC31\uDB40\uDC37\uDB40\uDC33\uDB40\uDC3E",
    "12": "\uDB40\uDC3CAffectueusement connu comme un \"point de repère\" pour les pilotes de l'Alliance Rebelle et de la Nouvelle République, le pilote de chasse de l'aile Y est déployé comme un chasseur-bombardier, conçu pour se battre jusqu'à son objectif, livrer sa charge utile d'explosifs lourds et se battre de nouveau pour sortir de l'avion. Son armement comprend deux canons laser, deux canons ioniques et deux lance-torpilles protoniques. Un droid astromech, tel qu'une unité R2, peut être branché dans une prise située derrière le poste de pilotage afin d'agir comme co-pilote et de gérer les divers systèmes du navire.\uDB40\uDC40\uDB40\uDC32\uDB40\uDC39\uDB40\uDC33\uDB40\uDC36\uDB40\uDC5F\uDB40\uDC31\uDB40\uDC37\uDB40\uDC33\uDB40\uDC3E",
    "13": "\uDB40\uDC3CUn assez bon droid pour coordonner les attaques. Pas doué pour se battre, juste pour planifier.\uDB40\uDC40\uDB40\uDC32\uDB40\uDC39\uDB40\uDC33\uDB40\uDC37\uDB40\uDC5F\uDB40\uDC31\uDB40\uDC37\uDB40\uDC33\uDB40\uDC3E",
    "2": "\uDB40\uDC3CConçus pour entretenir les podracers, les droïdes à fosse sont des droïdes de réparation durables et abordables. Les gouttelettes sont placées à une hauteur de 1,19 mètre, mais elles peuvent se replier sous une forme compacte lorsqu'elles ne sont pas utilisées. Cette fonction peut être contrebalancée en tapotant leur nez.\uDB40\uDC40\uDB40\uDC32\uDB40\uDC39\uDB40\uDC32\uDB40\uDC36\uDB40\uDC5F\uDB40\uDC31\uDB40\uDC37\uDB40\uDC33\uDB40\uDC3E",
    "3": "\uDB40\uDC3CLe modèle de droid 2-1B est très avancé et intelligent, et sa programmation est plus avancée par certains des meilleurs médecins de la galaxie de l'Académie médicale de l'État de Rhénanie, qui intègre également des processeurs heuristiques. La caractéristique la plus utile des droïdes 2-1B est la facilité avec laquelle les propriétaires peuvent mettre à jour leur programmation et leurs appendices. Une droïde 2-1B peut facilement devenir un spécialiste en neurochirurgie, en podiatrie, en pédiatrie, en remplacement de membres cybernétiques et en biologie extraterrestre avec un voyage dans un centre de services certifié.\uDB40\uDC40\uDB40\uDC32\uDB40\uDC39\uDB40\uDC32\uDB40\uDC37\uDB40\uDC5F\uDB40\uDC31\uDB40\uDC37\uDB40\uDC33\uDB40\uDC3E",
    "4": "\uDB40\uDC3CUne guerre en chrome battue, IG-88 mesure 1,96 mètres de hauteur. Son objectif constant, ainsi que sa capacité à suivre des cibles à l'aide de capteurs avancés qui lui font sonner la tête et lui permettent de voir dans toutes les directions, lui donnent un grand succès. Ces capteurs comprennent de multiples photorécepteurs rouges, un capteur de chaleur et un capteur de son IG-88 a également un codeur à la base de sa tête. Son torse peut tourner complètement sur le champ de bataille, ce qui lui permet de faire exploser des ennemis de tous les côtés. Son corps en métal dur lui permet de survivre à la plupart des attaques sans subir de dommages et il est muni de fils asservissants à l'épreuve de l'acide.\uDB40\uDC40\uDB40\uDC32\uDB40\uDC39\uDB40\uDC32\uDB40\uDC38\uDB40\uDC5F\uDB40\uDC31\uDB40\uDC37\uDB40\uDC33\uDB40\uDC3E",
    "5": "\uDB40\uDC3CPlusieurs nouveautés ont été ajoutées à la structure originale de Sphyrna, dont deux modules supplémentaires montés sur le port et à l'embarcadère de l'embarcation, six gousses d'évacuation en lieu et place de la baie de fret, et une quatrième conduite sous-lumineuse montée sur les trois premiers, lui donnant suffisamment de puissance pour déplacer un Star Destroyer handicapé. 315 mètres de longueur avec une accélération maximale de 900 kilomètres par heure. Équipé d'un système d'entraînement hyper-dynamique.\uDB40\uDC40\uDB40\uDC32\uDB40\uDC39\uDB40\uDC32\uDB40\uDC39\uDB40\uDC5F\uDB40\uDC31\uDB40\uDC37\uDB40\uDC33\uDB40\uDC3E",
    "6": "\uDB40\uDC3CDestiné à faciliter les réparations à bord, le droid de réparation G2 de deuxième degré est de petite taille, il mesure 0,8 mètre de hauteur. C'est aussi squat, avec une position large et lourde du fond qui le force à s'agiter quand il marchait. Ces traits, combinés à son long cou à plusieurs jointures et à ses pieds largement espacés et distribués en poids, lui valent le surnom de \"droïde d'oie\". Chaque unité G2 est dotée d'un cadre squelettique dénudé, couleur argent et laiton, avec des joints et un câblage exposés, avec une garniture colorée. Les manipulateurs lourds à trois chiffres du droid peuvent saisir la plupart des outils de réparation, tandis que les pieds joués aident à stabiliser son bas centre de gravité et assurent une stabilité supplémentaire au G2 lorsqu'il s'agit de gros équipements lourds.\uDB40\uDC40\uDB40\uDC32\uDB40\uDC39\uDB40\uDC33\uDB40\uDC30\uDB40\uDC5F\uDB40\uDC31\uDB40\uDC37\uDB40\uDC33\uDB40\uDC3E",
    "7": "\uDB40\uDC3CMesurant 150 mètres de long, il possède deux tourelles à deux et quatre turbolaser simples et a la capacité d'atteindre une vitesse maximale de 950 km/h. Selon Luke Skywalker, certains navires CR90 équipés de dispositifs de combat peuvent être équipés de six turbolasers doubles. Capable de transporter toute une escorte diplomatique, il a une capacité de passagers de plusieurs centaines. Bien que les navires ne soient pas construits comme porte-avions, trois intercepteurs à ailes A RZ-1 peuvent être fixés aux anneaux d'accostage, ce qui permet une petite escorte. Ils sont la colonne vertébrale de la première rébellion et de l'Alliance. Bien qu'ils ne soient pas particulièrement armés, les CR90 possèdent assez de puissance de feu avancée pour détruire assez facilement un croiseur de classe Gozanti.\uDB40\uDC40\uDB40\uDC32\uDB40\uDC39\uDB40\uDC33\uDB40\uDC31\uDB40\uDC5F\uDB40\uDC31\uDB40\uDC37\uDB40\uDC33\uDB40\uDC3E",
    "8": "\uDB40\uDC3CLe Speeder Bike de 74-Z est capable d'atteindre des vitesses allant jusqu'à 500 kilomètres à l'heure et a un plafond de vol de 25 mètres. 74-Zs est la variante militaire du civil 74-Y. Ils sont contrôlés par des guidons situés vers l'avant du véhicule, et des pédales de pied inclinées sous la pente ajustent la vitesse et l'altitude. Les véhicules hautement manoeuvrables sont équipés de capteurs et de dispositifs de communication situés entre les guidons, y compris d'un comlink et d'un brouilleur de comlink. Le haut-parleur est équipé de capteurs de suivi du relief qui se lient au HUD dans le casque du conducteur. Ils sont armés d'un canon à tambour tournant vers l'avant pour le combat.\uDB40\uDC40\uDB40\uDC32\uDB40\uDC39\uDB40\uDC33\uDB40\uDC32\uDB40\uDC5F\uDB40\uDC31\uDB40\uDC37\uDB40\uDC33\uDB40\uDC3E",
    "9": "\uDB40\uDC3CMesurant 5,47 mètres de long, l'ETA-2 est un starfighter très maniable orienté combat et est plus rapide que son prédécesseur d'Aethersprite, avec des moteurs à ions jumeaux offrant une accélération maximale de 5 200G et une vitesse maximale de 1 500 km/h. L'Eta-2 comporte des ailes avec des panneaux de radiateur supérieurs et inférieurs, des feuilles de S, qui sont ouvertes pour évacuer la chaleur excessive des moteurs du navire. Les ailes du radiateur s'ouvrent principalement lors de combats intenses. Pour sa défense, le navire comportait deux canons laser et deux canons ioniques. Contrairement aux canons laser, les canons ioniques du navire tirent des éclats de plasma qui causent des perturbations électriques temporaires à leur cible lors de l'impact.\uDB40\uDC40\uDB40\uDC32\uDB40\uDC39\uDB40\uDC33\uDB40\uDC33\uDB40\uDC5F\uDB40\uDC31\uDB40\uDC37\uDB40\uDC33\uDB40\uDC3E"
  },
  "title": {
    "1": "\uDB40\uDC3CAmbassadeur 3P0\uDB40\uDC40\uDB40\uDC32\uDB40\uDC39\uDB40\uDC31\uDB40\uDC32\uDB40\uDC5F\uDB40\uDC31\uDB40\uDC37\uDB40\uDC33\uDB40\uDC3E",
    "10": "\uDB40\uDC3CDroid série R3\uDB40\uDC40\uDB40\uDC32\uDB40\uDC39\uDB40\uDC32\uDB40\uDC31\uDB40\uDC5F\uDB40\uDC31\uDB40\uDC37\uDB40\uDC33\uDB40\uDC3E",
    "11": "\uDB40\uDC3CT-70 X-Wing\uDB40\uDC40\uDB40\uDC32\uDB40\uDC39\uDB40\uDC32\uDB40\uDC32\uDB40\uDC5F\uDB40\uDC31\uDB40\uDC37\uDB40\uDC33\uDB40\uDC3E",
    "12": "\uDB40\uDC3CBatteur à ailes Y\uDB40\uDC40\uDB40\uDC32\uDB40\uDC39\uDB40\uDC32\uDB40\uDC33\uDB40\uDC5F\uDB40\uDC31\uDB40\uDC37\uDB40\uDC33\uDB40\uDC3E",
    "13": "\uDB40\uDC3CDroid super-tactique\uDB40\uDC40\uDB40\uDC32\uDB40\uDC39\uDB40\uDC32\uDB40\uDC34\uDB40\uDC5F\uDB40\uDC31\uDB40\uDC37\uDB40\uDC33\uDB40\uDC3E",
    "2": "\uDB40\uDC3CDroid série DUM\uDB40\uDC40\uDB40\uDC32\uDB40\uDC39\uDB40\uDC31\uDB40\uDC33\uDB40\uDC5F\uDB40\uDC31\uDB40\uDC37\uDB40\uDC33\uDB40\uDC3E",
    "3": "\uDB40\uDC3CDroïde chirurgical 2-1B\uDB40\uDC40\uDB40\uDC32\uDB40\uDC39\uDB40\uDC31\uDB40\uDC34\uDB40\uDC5F\uDB40\uDC31\uDB40\uDC37\uDB40\uDC33\uDB40\uDC3E",
    "4": "\uDB40\uDC3CIG-88B Droid\uDB40\uDC40\uDB40\uDC32\uDB40\uDC39\uDB40\uDC31\uDB40\uDC35\uDB40\uDC5F\uDB40\uDC31\uDB40\uDC37\uDB40\uDC33\uDB40\uDC3E",
    "5": "\uDB40\uDC3CSphyrna Corvette\uDB40\uDC40\uDB40\uDC32\uDB40\uDC39\uDB40\uDC31\uDB40\uDC36\uDB40\uDC5F\uDB40\uDC31\uDB40\uDC37\uDB40\uDC33\uDB40\uDC3E",
    "6": "\uDB40\uDC3CG2 Réparation Droid\uDB40\uDC40\uDB40\uDC32\uDB40\uDC39\uDB40\uDC31\uDB40\uDC37\uDB40\uDC5F\uDB40\uDC31\uDB40\uDC37\uDB40\uDC33\uDB40\uDC3E",
    "7": "\uDB40\uDC3CCR90 Corvette\uDB40\uDC40\uDB40\uDC32\uDB40\uDC39\uDB40\uDC31\uDB40\uDC38\uDB40\uDC5F\uDB40\uDC31\uDB40\uDC37\uDB40\uDC33\uDB40\uDC3E",
    "8": "\uDB40\uDC3CVitesse de vitesse 74-Z\uDB40\uDC40\uDB40\uDC32\uDB40\uDC39\uDB40\uDC31\uDB40\uDC39\uDB40\uDC5F\uDB40\uDC31\uDB40\uDC37\uDB40\uDC33\uDB40\uDC3E",
    "9": "\uDB40\uDC3CIntercepteur ETA-2\uDB40\uDC40\uDB40\uDC32\uDB40\uDC39\uDB40\uDC32\uDB40\uDC30\uDB40\uDC5F\uDB40\uDC31\uDB40\uDC37\uDB40\uDC33\uDB40\uDC3E"
  }
}